LMTuner/__init__.py
LMTuner/__main__.py
LMTuner/argments.py
LMTuner/dataset.py
LMTuner/deepspeed_file.py
LMTuner/inference.py
LMTuner/initialize.py
LMTuner/lomo.py
LMTuner/lora.py
LMTuner/setting.py
LMTuner/trainer.py
LMTuner/utils.py
LMTuner/kernels/__init__.py
LMTuner/models/GLM130B_model.py
LMTuner/models/GPT2_model.py
LMTuner/models/GPTNeo_model.py
LMTuner/models/LLAMA_model.py
LMTuner/models/LLAMAv2_model.py
LMTuner/models/__init__.py
LMTuner/models/basemodel.py
LMTuner/models/model_io.py
LMTuner/models/transformers_model.py
LMTuner/quantization/__init__.py
LMTuner/quantization/functional.py
LMTuner/quantization/layers.py
LMTuner/scaled_rope/__init__.py
LMTuner/scaled_rope/configuration_llama.py
LMTuner/scaled_rope/modelling_llama.py
LMTuner-1.2.0.dist-info/LICENSE
LMTuner-1.2.0.dist-info/METADATA
LMTuner-1.2.0.dist-info/WHEEL
LMTuner-1.2.0.dist-info/top_level.txt
LMTuner-1.2.0.dist-info/RECORD
