Metadata-Version: 2.1
Name: LMTuner
Version: 1.2.0
Summary: No More Complications, Effortless LLM Training with LMTuner
Home-page: https://github.com/WENGSYX/LMTuner
Author: Yixuan Weng
Author-email: wengsyx@gmail.com
License-File: LICENSE
Requires-Dist: transformers (>=4.30.2)
Requires-Dist: numpy
Requires-Dist: datasets
Requires-Dist: torch
Requires-Dist: nvidia-ml-py
Requires-Dist: sentencepiece
Requires-Dist: openai (>=0.27.8)
